skutterbug/__init__.py
skutterbug/agent.py
skutterbug/uri/__init__.py
skutterbug/uri/public_suffix_list.dat
skutterbug/uri/publicsuffix.py
skutterbug-0.0.1.dist-info/LICENSE
skutterbug-0.0.1.dist-info/WHEEL
skutterbug-0.0.1.dist-info/METADATA
skutterbug-0.0.1.dist-info/RECORD
